bt856a/__init__.py
bt856a/console.py
bt856a/meter.py
bt856a-0.1.0.dist-info/LICENSE
bt856a-0.1.0.dist-info/METADATA
bt856a-0.1.0.dist-info/WHEEL
bt856a-0.1.0.dist-info/entry_points.txt
bt856a-0.1.0.dist-info/RECORD
