Metadata-Version: 2.1
Name: bt856a
Version: 0.1.0
Summary: A python library for interfacing with BTMETER BT-856A Anemometer
License: MIT
Author: Simon Billemont
Author-email: simon@angelcorp.be
Classifier: License :: OSI Approved :: MIT License
Classifier: Programming Language :: Python :: 2
Classifier: Programming Language :: Python :: 2.7
Classifier: Programming Language :: Python :: 3
Classifier: Programming Language :: Python :: 3.4
Classifier: Programming Language :: Python :: 3.5
Classifier: Programming Language :: Python :: 3.6
Classifier: Programming Language :: Python :: 3.7
Classifier: Programming Language :: Python :: 3.8
Classifier: Programming Language :: Python :: 3.9
Classifier: Programming Language :: Python :: 3.10
Classifier: Programming Language :: Python :: 3.11
Classifier: Programming Language :: Python :: 3.12
Requires-Dist: aenum (>=3.1,<4.0)
Requires-Dist: paho-mqtt (>=2.1,<3.0)
Requires-Dist: pyserial (>=3,<4)
